{
  "pages": [
    {
      "title": "Raspi-Report",
      "file": "raspi_report/raspi_report.html"
    },
    {
      "title": "Webcam Images",
      "file": "webcam/webcam_images.html"
    },
    {
      "title": "Table Statistics Report",
      "file": "weather/table_statistics.html"
    },
    {
      "title": "Day Dashboard",
      "file": "weather/day.html"
    },
    {
      "title": "Week Dashboard",
      "file": "weather/week.html"
    },
    {
      "title": "Month WeatherDashboard",
      "file": "weather/month.html"
    },
    {
      "title": "Year Weather Dashboard",
      "file": "weather/year.html"
    }
  ]
}